LICENSE
README.md
setup.cfg
setup.py
blogger/__init__.py
blogger/cli.py
blogger.egg-info/PKG-INFO
blogger.egg-info/SOURCES.txt
blogger.egg-info/dependency_links.txt
blogger.egg-info/entry_points.txt
blogger.egg-info/requires.txt
blogger.egg-info/top_level.txt
blogger/commands/__init__.py
blogger/commands/audio.py
blogger/commands/base.py
blogger/commands/converters.py
blogger/commands/providers.py
blogger/commands/voices.py
blogger/converters/__init__.py
blogger/converters/basic_converter.py
blogger/converters/converter.py
blogger/converters/gtts_converter.py
blogger/providers/__init__.py
blogger/providers/base.py
blogger/providers/ghost.py
blogger/providers/manual.py
blogger/providers/medium.py
blogger/utils/__init__.py
blogger/utils/string.py